{
  "source_id": "af50edb92452",
  "hash": "af50edb92452069f203b993489572519da434fcf1469536694b74231bb48417c",
  "original_name": "clip_8682498476_46.clip",
  "ingested_at": "2026-04-14T17:43:15.173091+00:00",
  "clip_source": true,
  "fetch_url": "https://github.com/ProxySoul/soulforge",
  "fetch_final_url": "https://github.com/ProxySoul/soulforge",
  "fetch_status": "ok",
  "fetch_error": null,
  "fetched_title": "GitHub - proxysoul/soulforge: Graph-powered code intelligence, multi-agent coding with codebase-aware AI. No more grep & pray · GitHub",
  "shared_title": null,
  "user_comment": "proxysoul/soulforge: Graph-powered code intelligence, multi-agent coding with codebase-aware AI. No more grep & pray",
  "normalized_url": "https://github.com/ProxySoul/soulforge"
}
